custom_gameclock/__init__.py
custom_gameclock/clock.py
custom_gameclock/defaults.py
custom_gameclock/errors.py
custom_gameclock/formatting.py
custom_gameclock/functions.py
custom_gameclock/mixins.py
custom_gameclock/vocabulary.py
custom_gameclock-1.1.1.dist-info/LICENSE
custom_gameclock-1.1.1.dist-info/METADATA
custom_gameclock-1.1.1.dist-info/WHEEL
custom_gameclock-1.1.1.dist-info/top_level.txt
custom_gameclock-1.1.1.dist-info/RECORD
